<?xml version="1.0" encoding="UTF-8"?>
<ae:configurations
    xmlns:ae="http://agavi.org/agavi/config/global/envelope/1.0"
    xmlns="http://agavi.org/agavi/config/parts/translation/1.0"
    xmlns:xi="http://www.w3.org/2001/XInclude"
>
    <ae:configuration>

        <available_locales default_locale="de_DE">
            <available_locale identifier="de_DE">
                <ae:parameter name="description">Deutsch</ae:parameter>
            </available_locale>
            <available_locale identifier="en_GB">
                <ae:parameter name="description">English GB</ae:parameter>
            </available_locale>
            <available_locale identifier="en_US">
                <ae:parameter name="description">English US</ae:parameter>
            </available_locale>
            <available_locale identifier="ar_AR">
                <ae:parameter name="description">Arabic</ae:parameter>
            </available_locale>
        </available_locales>

        <translators default_domain="date_formats">
            <translator domain="date_formats">
                <translator domain="datetime">
                    <date_formatter>
                        <ae:parameters>
                            <ae:parameter name="type">datetime</ae:parameter>
                            <ae:parameter name="format">yyyy-MM-dd HH:mm:ss</ae:parameter>
                        </ae:parameters>
                    </date_formatter>
                </translator>
            </translator>
        </translators>
    </ae:configuration>

    <ae:configuration>
        <translators default_domain="application.ui">
            <translator domain="application">
                <message_translator class="AgaviSimpleTranslator">

                    <ae:parameter name="pagination">
                        <ae:parameter name="de">
                            <ae:parameter name="pager.description">Seite %s von %s</ae:parameter>
                            <ae:parameter name="pager.first_page.title">Erste</ae:parameter>
                            <ae:parameter name="pager.prev_page.title">Vorherige</ae:parameter>
                            <ae:parameter name="pager.jump_to_page.title">Los</ae:parameter>
                            <ae:parameter name="pager.next_page.title">Nächste</ae:parameter>
                            <ae:parameter name="pager.last_page.title">Letzte</ae:parameter>
                        </ae:parameter>
                        <ae:parameter name="en">
                            <ae:parameter name="pager.description">Page %s of %s</ae:parameter>
                            <ae:parameter name="pager.first_page.title">First</ae:parameter>
                            <ae:parameter name="pager.prev_page.title">Previous</ae:parameter>
                            <ae:parameter name="pager.jump_to_page.title">Go</ae:parameter>
                            <ae:parameter name="pager.next_page.title">Next</ae:parameter>
                            <ae:parameter name="pager.last_page.title">Last</ae:parameter>
                        </ae:parameter>
                    </ae:parameter>

                    <ae:parameter name="hrte">
                        <ae:parameter name="de">
                            <ae:parameter name="bold">Fett</ae:parameter>
                            <ae:parameter name="bold.title">Fettgedruckt (Strg+B)</ae:parameter>
                            <ae:parameter name="italic">Kursiv</ae:parameter>
                            <ae:parameter name="italic.title">Kursiv (Strg+I)</ae:parameter>
                            <ae:parameter name="underline">Unterstrichen</ae:parameter>
                            <ae:parameter name="underline.title">Unterstrichen (Strg+U)</ae:parameter>
                            <ae:parameter name="strike">Durchgestrichen</ae:parameter>
                            <ae:parameter name="strike.title">Durchgestrichen</ae:parameter>
                            <ae:parameter name="link">Verlinkung</ae:parameter>
                            <ae:parameter name="link.title">Link erstellen/ändern</ae:parameter>
                            <ae:parameter name="unlink">Link entfernen</ae:parameter>
                            <ae:parameter name="unlink.title">Bestehende Verlinkung aufheben</ae:parameter>
                            <ae:parameter name="ol">OL</ae:parameter>
                            <ae:parameter name="ol.title">Nummerierter Listenpunkt</ae:parameter>
                            <ae:parameter name="ul">UL</ae:parameter>
                            <ae:parameter name="ul.title">Unnummerierter Listenpunkt</ae:parameter>
                            <ae:parameter name="undo">Undo</ae:parameter>
                            <ae:parameter name="undo.title">Letzte Aktion rückgängig machen (Strg+Z)</ae:parameter>
                            <ae:parameter name="redo">Redo</ae:parameter>
                            <ae:parameter name="redo.title">Letzte Aktion wiederherstellen (Strg+Y)</ae:parameter>
                            <ae:parameter name="autogrow"><![CDATA[&#x21D5;]]></ae:parameter>
                            <ae:parameter name="autogrow.title">Automatisch die Größe des Textfelds anpassen?</ae:parameter>
                            <ae:parameter name="popup-link.accept">Übernehmen</ae:parameter>
                            <ae:parameter name="popup-link.cancel">Abbrechen</ae:parameter>
                            <ae:parameter name="popup-link.header">Verlinkung setzen</ae:parameter>
                            <ae:parameter name="popup-link.href-input.label">Adresse:</ae:parameter>
                            <ae:parameter name="popup-link.href-input.title">Bitte komplette URL inklusive Protokoll eingeben (z.B. http://example.com)</ae:parameter>
                            <ae:parameter name="popup-link.href-input.placeholder">Link URL (http://example.com)</ae:parameter>
                            <ae:parameter name="popup-link.title-input.label">Titel:</ae:parameter>
                            <ae:parameter name="popup-link.title-input.title">Bitte Titel für den Link angeben</ae:parameter>
                            <ae:parameter name="popup-link.target-input.label">Link in neuem Fenster/Tab öffnen</ae:parameter>
                        </ae:parameter>
                        <ae:parameter name="en">
                            <ae:parameter name="bold">Bold</ae:parameter>
                            <ae:parameter name="bold.title">Toggle bold (Ctrl+B)</ae:parameter>
                            <ae:parameter name="italic">Italic</ae:parameter>
                            <ae:parameter name="italic.title">Toggle italic (Ctrl+I)</ae:parameter>
                            <ae:parameter name="underline">Underline</ae:parameter>
                            <ae:parameter name="underline.title">Toggle underline (Ctrl+U)</ae:parameter>
                            <ae:parameter name="strike">Strikethrough</ae:parameter>
                            <ae:parameter name="strike.title">Toggle strikethrough</ae:parameter>
                            <ae:parameter name="link">Link</ae:parameter>
                            <ae:parameter name="link.title">Add or modify link</ae:parameter>
                            <ae:parameter name="unlink">Remove Link</ae:parameter>
                            <ae:parameter name="unlink.title">Remove existing link</ae:parameter>
                            <ae:parameter name="ol">OL</ae:parameter>
                            <ae:parameter name="ol.title">Ordered list</ae:parameter>
                            <ae:parameter name="ul">UL</ae:parameter>
                            <ae:parameter name="ul.title">Unordered list</ae:parameter>
                            <ae:parameter name="undo">Undo</ae:parameter>
                            <ae:parameter name="undo.title">Undo last operation (Ctrl+Z)</ae:parameter>
                            <ae:parameter name="redo">Redo</ae:parameter>
                            <ae:parameter name="redo.title">Redo last operation (Ctrl+Y)</ae:parameter>
                            <ae:parameter name="autogrow"><![CDATA[&#x21D5;]]></ae:parameter>
                            <ae:parameter name="autogrow.title">Automatically grow height of text input area?</ae:parameter>
                            <ae:parameter name="popup-link.accept">Accept</ae:parameter>
                            <ae:parameter name="popup-link.cancel">Cancel</ae:parameter>
                            <ae:parameter name="popup-link.header">Modify Link</ae:parameter>
                            <ae:parameter name="popup-link.href-input.label">URL:</ae:parameter>
                            <ae:parameter name="popup-link.href-input.title">Please input a valid URL including the protocol (e.g. http://example.com)</ae:parameter>
                            <ae:parameter name="popup-link.href-input.placeholder">Link URL (http://example.com)</ae:parameter>
                            <ae:parameter name="popup-link.title-input.label">Title:</ae:parameter>
                            <ae:parameter name="popup-link.title-input.title">Please input a title for the link</ae:parameter>
                            <ae:parameter name="popup-link.target-input.label">Open link in new window</ae:parameter>
                        </ae:parameter>
                    </ae:parameter>

                    <ae:parameter name="activities">
                        <ae:parameter name="de">
                            <ae:parameter name="search.description">Datensätze durchstöbern</ae:parameter>
                            <ae:parameter name="search.label">Suche</ae:parameter>
                        </ae:parameter>
                        <ae:parameter name="en">
                            <ae:parameter name="search.description">Search</ae:parameter>
                            <ae:parameter name="search.label">Search terms</ae:parameter>
                        </ae:parameter>
                    </ae:parameter>

                    <ae:parameter name="ui">
                        <ae:parameter name="de">
                            <ae:parameter name="brand_entity">Honeybee</ae:parameter>
                            <ae:parameter name="brand_title">Honeybee CMF</ae:parameter>
                            <ae:parameter name="menu">Menü</ae:parameter>
                            <ae:parameter name="go_to_dashboard">Zur Einstiegsseite…</ae:parameter>
                            <ae:parameter name="welcome_header">Willkommen im Honeybee CMF</ae:parameter>
                            <ae:parameter name="there_were_errors">There were errors</ae:parameter>
                            <!-- View: collection / hierarchy -->
                            <ae:parameter name="sort_by">Sortieren nach</ae:parameter>
                            <ae:parameter name="sidebar">Sidebar</ae:parameter>
                            <ae:parameter name="activities">Activities</ae:parameter>
                            <ae:parameter name="cannot_display_collection">Can't display collection</ae:parameter>
                            <!-- View: hierarchy -->
                            <ae:parameter name="parent_resource">Parent resource</ae:parameter>
                            <ae:parameter name="child_resources">Child resources</ae:parameter>
                            <ae:parameter name="root_resources">Root resources</ae:parameter>
                            <!-- View: sumary -->
                            <ae:parameter name="summary">Summary</ae:parameter>
                            <ae:parameter name="summary_error">Summary/SummaryError</ae:parameter>
                            <!-- Component: embed_actions -->
                            <ae:parameter name="delete_action">Löschen</ae:parameter>
                            <ae:parameter name="duplicate_action">duplizieren</ae:parameter>
                            <ae:parameter name="move_up_action">nach oben</ae:parameter>
                            <ae:parameter name="move_down_action">nach unten</ae:parameter>
                            <ae:parameter name="none_action">keine Action</ae:parameter>
                        </ae:parameter>
                        <ae:parameter name="en">
                            <ae:parameter name="brand-name">Honeybee</ae:parameter>
                            <ae:parameter name="brand-title">Honeybee CMF</ae:parameter>
                            <ae:parameter name="menu">Menu</ae:parameter>
                            <ae:parameter name="go_to_dashboard">Go to the dashboard…</ae:parameter>
                            <ae:parameter name="welcome_header">Welcome to the Honeybee CMF</ae:parameter>
                            <ae:parameter name="there_were_errors">There were errors</ae:parameter>
                            <!-- View: collection / hierarchy -->
                            <ae:parameter name="sort_by">Sort by</ae:parameter>
                            <ae:parameter name="sidebar">Sidebar</ae:parameter>
                            <ae:parameter name="activities">Activities</ae:parameter>
                            <ae:parameter name="cannot_display_collection">Can't display collection</ae:parameter>
                            <!-- View: hierarchy -->
                            <ae:parameter name="parent_resource">Parent resource</ae:parameter>
                            <ae:parameter name="child_resources">Child resources</ae:parameter>
                            <ae:parameter name="root_resources">Root resources</ae:parameter>
                            <!-- View: sumary -->
                            <ae:parameter name="summary">Summary</ae:parameter>
                            <ae:parameter name="summary_error">Summary/SummaryError</ae:parameter>
                            <!-- Component: embed_actions -->
                            <ae:parameter name="delete_action">Delete</ae:parameter>
                            <ae:parameter name="duplicate_action">Duplicate</ae:parameter>
                            <ae:parameter name="move_up_action">Move up</ae:parameter>
                            <ae:parameter name="move_down_action">Move down</ae:parameter>
                            <ae:parameter name="none_action">Do nothing</ae:parameter>
                        </ae:parameter>
                    </ae:parameter>
                    <ae:parameter name="roles">
                        <ae:parameter name="de">
                            <ae:parameter name="non-privileged">Nutzer ohne Rechte</ae:parameter>
                            <ae:parameter name="full-privileged">Nutzer mit allen Rechten</ae:parameter>
                        </ae:parameter>
                    </ae:parameter>
                </message_translator>
            </translator>
<!--
            <message_translator class="AgaviGettextTranslator">
                <ae:parameter name="text_domains">
                    <ae:parameter name="menu">%core.app_dir%/data/i18n</ae:parameter>
                    <ae:parameter name="layout">%core.app_dir%/data/i18n</ae:parameter>
                    <ae:parameter name="Login">%core.app_dir%/data/i18n</ae:parameter>
                    <ae:parameter name="SearchEngineSpam">%core.app_dir%/data/i18n</ae:parameter>
                    <ae:parameter name="ErrorActions">%core.app_dir%/data/i18n</ae:parameter>
                </ae:parameter>
            </message_translator>
-->
        </translators>

    </ae:configuration>
<!--
    <ae:configuration environment="development.*">
        <translators default_domain="default">
            <translator domain="default">
                <message_translator class="AgaviGettextTranslator">
                    <ae:parameter name="store_calls">%core.cache_dir%/data</ae:parameter>
                </message_translator>
            </translator>
        </translators>
    </ae:configuration>
-->

    <ae:configuration environment="testing.*">
        <xi:include href="../modules/Honeybee_SystemAccount/config/User/translation.xml" xpointer="xmlns(ae=http://agavi.org/agavi/config/global/envelope/1.0) xpointer(//ae:configuration/*)"/>
    </ae:configuration>

    <xi:include href="./includes/translation.xml"
        xpointer="xmlns(ae=http://agavi.org/agavi/config/global/envelope/1.0) xpointer(/ae:configurations/*)">
        <xi:fallback />
    </xi:include>

</ae:configurations>
